bigquery_mcp/__init__.py
bigquery_mcp/auth.py
bigquery_mcp/bigquery_tools.py
bigquery_mcp/query_safety.py
bigquery_mcp/server.py
bigquery_mcp-0.1.4.dist-info/METADATA
bigquery_mcp-0.1.4.dist-info/WHEEL
bigquery_mcp-0.1.4.dist-info/entry_points.txt
bigquery_mcp-0.1.4.dist-info/licenses/LICENSE
bigquery_mcp-0.1.4.dist-info/RECORD
