Metadata-Version: 2.4
Name: bigquery-mcp
Version: 0.1.4
Summary: BigQuery MCP server optimized for quick navigation of larger projects and datasets.
Project-URL: Homepage, https://pvoo.github.io/bigquery-mcp/
Project-URL: Repository, https://github.com/pvoo/bigquery-mcp
Project-URL: Documentation, https://pvoo.github.io/bigquery-mcp/
Author-email: Paul van Oorschot <fpgmaas@gmail.com>
License-Expression: MIT
License-File: LICENSE
Keywords: python
Classifier: Intended Audience :: Developers
Classifier: Programming Language :: Python
Classifier: Programming Language :: Python :: 3
Classifier: Programming Language :: Python :: 3.10
Classifier: Programming Language :: Python :: 3.11
Classifier: Programming Language :: Python :: 3.12
Classifier: Programming Language :: Python :: 3.13
Classifier: Topic :: Software Development :: Libraries :: Python Modules
Requires-Python: <4.0,>=3.10
Requires-Dist: fastmcp==2.13.0
Requires-Dist: google-cloud-bigquery==3.31.0
Requires-Dist: python-dotenv>=1.1.0
